munchkin/__about__.py
munchkin/__init__.py
munchkin/cli.py
munchkin/munchkin.py
munchkin/__about__.pyc
munchkin/__init__.pyc
munchkin/munchkin.pyc
munchkin/core/__init__.py
munchkin/core/card.py
munchkin/core/utils.py
munchkin/core/__init__.pyc
munchkin/core/card.pyc
munchkin/core/utils.pyc
munchkin/core/strategies/__init__.py
munchkin/core/strategies/angled.py
munchkin/core/strategies/bottom_to_top.py
munchkin/core/strategies/diagonal.py
munchkin/core/strategies/left_to_right.py
munchkin/core/strategies/right_to_left.py
munchkin/core/strategies/spiral.py
munchkin/core/strategies/top_to_down.py
munchkin/core/strategies/zig_zag.py
munchkin/core/strategies/zig_zag_reverse.py
munchkin/core/strategies/__init__.pyc
munchkin/core/strategies/angled.pyc
munchkin/core/strategies/bottom_to_top.pyc
munchkin/core/strategies/diagonal.pyc
munchkin/core/strategies/left_to_right.pyc
munchkin/core/strategies/right_to_left.pyc
munchkin/core/strategies/spiral.pyc
munchkin/core/strategies/top_to_down.pyc
munchkin/core/strategies/zig_zag.pyc
munchkin/core/strategies/zig_zag_reverse.pyc
munchkin/lib/__init__.py
munchkin/lib/__init__.pyc
munchkin/lib/passwordcard/__init__.py
munchkin/lib/passwordcard/javarandom.py
munchkin/lib/passwordcard/passwordcard.py
munchkin/lib/passwordcard/__init__.pyc
munchkin/lib/passwordcard/javarandom.pyc
munchkin/lib/passwordcard/passwordcard.pyc
munchkin-0.3.2.dist-info/top_level.txt
munchkin-0.3.2.dist-info/entry_points.txt
munchkin-0.3.2.dist-info/METADATA
munchkin-0.3.2.dist-info/DESCRIPTION.rst
munchkin-0.3.2.dist-info/metadata.json
munchkin-0.3.2.dist-info/WHEEL
munchkin-0.3.2.dist-info/RECORD
