Metadata-Version: 2.0
Name: munchkin
Version: 0.3.2
Summary: Wordlist generator based on password cards
Home-page: https://github.com/gszathmari/munchkin
Author: Gabor Szathmari
Author-email: gszathmari@gmail.com
License: MIT
Keywords: security password
Platform: Linux
Classifier: Development Status :: 4 - Beta
Classifier: License :: OSI Approved :: MIT License
Classifier: Topic :: Security
Classifier: Intended Audience :: Other Audience
Classifier: Programming Language :: Python :: 2 :: Only
Classifier: Programming Language :: Python :: 2.6
Classifier: Programming Language :: Python :: 2.7
Requires-Dist: numpy (==1.9.3)
Requires-Dist: colorama
